pyterrain/__init__.py
pyterrain/core.py
pyterrain-0.0.2.dist-info/LICENSE
pyterrain-0.0.2.dist-info/METADATA
pyterrain-0.0.2.dist-info/WHEEL
pyterrain-0.0.2.dist-info/top_level.txt
pyterrain-0.0.2.dist-info/RECORD
