Metadata-Version: 2.1
Name: pyterrain
Version: 0.0.2
Summary: A Python package to fetch terrain data easily.
Home-page: https://github.com/Clarmy/pyterrain
Author: Wentao Li
Author-email: 
Classifier: Programming Language :: Python :: 3
Requires-Python: >=3.8
License-File: LICENSE
Requires-Dist: numpy (>=1.24.1)
Requires-Dist: requests (>=2.28.1)
Requires-Dist: mercantile (>=1.2.1)
Requires-Dist: tqdm (>=4.64.1)
Requires-Dist: pyproj (>=3.4.1)
Requires-Dist: matplotlib (>=3.6.2)
Requires-Dist: retrying
Requires-Dist: loguru
